{
"type": "FeatureCollection",
"name": "myjobs",
"crs": { "type": "name", "properties": { "name": "urn:ogc:def:crs:OGC:1.3:CRS84" } },
"features": [
{ "type": "Feature", "properties": { "id": 1 }, "geometry": { "type": "Point", "coordinates": [ -79.046067852027932, 35.910891406459335 ] } },
{ "type": "Feature", "properties": { "id": 2 }, "geometry": { "type": "Point", "coordinates": [ -79.051201317360892, 35.911379042115499 ] } }
]
}
